[{"position": 1, "teamID": "62", "teamEngName": "Al-Duhail SC", "teamArName": "\u0646\u0627\u062f\u064a \u0627\u0644\u062f\u062d\u064a\u0644", "matchesPlayed": 5, "wins": 4, "draws": 1, "losses": 0, "goalsFor": 18, "goalsAgainst": 8, "goalDifference": 10, "points": 13}, {"position": 2, "teamID": "2", "teamEngName": "Al-Arabi SC", "teamArName": "\u0627\u0644\u0646\u0627\u062f\u064a \u0627\u0644\u0639\u0631\u0628\u064a", "matchesPlayed": 5, "wins": 3, "draws": 1, "losses": 1, "goalsFor": 6, "goalsAgainst": 4, "goalDifference": 2, "points": 10}, {"position": 3, "teamID": "3", "teamEngName": "Al-Gharafa SC", "teamArName": "\u0646\u0627\u062f\u064a \u0627\u0644\u063a\u0631\u0627\u0641\u0629", "matchesPlayed": 5, "wins": 2, "draws": 2, "losses": 1, "goalsFor": 8, "goalsAgainst": 6, "goalDifference": 2, "points": 8}, {"position": 4, "teamID": "100", "teamEngName": "Al-Rayyan SC", "teamArName": "\u0646\u0627\u062f\u064a \u0627\u0644\u0631\u064a\u0627\u0646", "matchesPlayed": 5, "wins": 1, "draws": 2, "losses": 2, "goalsFor": 9, "goalsAgainst": 11, "goalDifference": -2, "points": 5}, {"position": 5, "teamID": "4", "teamEngName": "Al-Shamal SC", "teamArName": "\u0646\u0627\u062f\u064a \u0627\u0644\u0634\u0645\u0627\u0644", "matchesPlayed": 5, "wins": 1, "draws": 1, "losses": 3, "goalsFor": 7, "goalsAgainst": 10, "goalDifference": -3, "points": 4}, {"position": 6, "teamID": "53", "teamEngName": "Al-Markhiya SC", "teamArName": "\u0646\u0627\u062f\u064a \u0627\u0644\u0645\u0631\u062e\u064a\u0629", "matchesPlayed": 5, "wins": 0, "draws": 1, "losses": 4, "goalsFor": 7, "goalsAgainst": 16, "goalDifference": -9, "points": 1}]